DarijaDistance/__initi__.py
DarijaDistance/data_loader.py
DarijaDistance/mappings.py
DarijaDistance/preprocess.py
DarijaDistance/word_distance.py
DarijaDistance/data/hash_table_sum.pickle
DarijaDistance/data/hash_table_word.pickle
DarijaDistance/data/list_of_sum_keys.pickle
DarijaDistance/data/names.csv
DarijaDistance/data/translations.csv
DarijaDistance-1.0.8.dist-info/LICENSE
DarijaDistance-1.0.8.dist-info/METADATA
DarijaDistance-1.0.8.dist-info/WHEEL
DarijaDistance-1.0.8.dist-info/top_level.txt
DarijaDistance-1.0.8.dist-info/RECORD
