Metadata-Version: 2.1
Name: DarijaDistance
Version: 1.0.8
Summary: A library for finding the closest words and calculating word distances for the Moroccan Dialect Darija
Home-page: https://github.com/aissam-out/DarijaDistance
Author: Aissam Outchakoucht
Author-email: aissam.outchakoucht@gmail.com
Classifier: Development Status :: 5 - Production/Stable
Classifier: Intended Audience :: Developers
Classifier: License :: OSI Approved :: MIT License
Classifier: Programming Language :: Python :: 3
Classifier: Programming Language :: Python :: 3.6
Classifier: Programming Language :: Python :: 3.7
Classifier: Programming Language :: Python :: 3.8
Classifier: Programming Language :: Python :: 3.9
Classifier: Programming Language :: Python :: 3.10
Classifier: Operating System :: OS Independent
Classifier: Topic :: Software Development :: Libraries :: Python Modules
Requires-Python: >=3.6
